[
  {
    "id": "a1f00101-aaaa-4a11-b111-000000000001",
    "type": "income",
    "amount": 1200,
    "category": "other",
    "description": "Monthly income payment",
    "date": "2024-01-05T07:00:00.000Z"
  },
  {
    "id": "a1f00102-aaaa-4a11-b111-000000000002",
    "type": "expense",
    "amount": 45,
    "category": "food",
    "description": "Groceries from local market",
    "date": "2024-02-10T18:30:00.000Z"
  },
  {
    "id": "a1f00103-aaaa-4a11-b111-000000000003",
    "type": "income",
    "amount": 300,
    "category": "other",
    "description": "Freelance project payment",
    "date": "2024-03-15T14:00:00.000Z"
  },
  {
    "id": "a1f00104-aaaa-4a11-b111-000000000004",
    "type": "expense",
    "amount": 60,
    "category": "transport",
    "description": "Monthly transportation costs",
    "date": "2024-04-02T11:20:00.000Z"
  },
  {
    "id": "a1f00105-aaaa-4a11-b111-000000000005",
    "type": "income",
    "amount": 150,
    "category": "other",
    "description": "Cashback and refunds",
    "date": "2024-05-20T09:00:00.000Z"
  },
  {
    "id": "a1f00106-aaaa-4a11-b111-000000000006",
    "type": "expense",
    "amount": 90,
    "category": "utilities",
    "description": "Electricity and water bill",
    "date": "2024-06-08T22:00:00.000Z"
  },
  {
    "id": "a1f00107-aaaa-4a11-b111-000000000007",
    "type": "income",
    "amount": 500,
    "category": "other",
    "description": "Side business income",
    "date": "2024-07-12T16:45:00.000Z"
  },
  {
    "id": "a1f00108-aaaa-4a11-b111-000000000008",
    "type": "expense",
    "amount": 120,
    "category": "shopping",
    "description": "Clothes and accessories",
    "date": "2024-08-19T13:10:00.000Z"
  },
  {
    "id": "a1f00109-aaaa-4a11-b111-000000000009",
    "type": "income",
    "amount": 200,
    "category": "other",
    "description": "Online sales earnings",
    "date": "2024-10-01T10:00:00.000Z"
  },
  {
    "id": "a1f00110-aaaa-4a11-b111-000000000010",
    "type": "expense",
    "amount": 75,
    "category": "health",
    "description": "Pharmacy and health products",
    "date": "2024-12-03T19:40:00.000Z"
  },

  {
    "id": "b2f00201-bbbb-4b22-b222-000000000011",
    "type": "income",
    "amount": 1300,
    "category": "other",
    "description": "Monthly income payment",
    "date": "2025-01-04T07:00:00.000Z"
  },
  {
    "id": "b2f00202-bbbb-4b22-b222-000000000012",
    "type": "expense",
    "amount": 55,
    "category": "food",
    "description": "Restaurant lunch",
    "date": "2025-02-14T15:00:00.000Z"
  },
  {
    "id": "b2f00203-bbbb-4b22-b222-000000000013",
    "type": "income",
    "amount": 400,
    "category": "other",
    "description": "Freelance consulting payment",
    "date": "2025-03-11T12:00:00.000Z"
  },
  {
    "id": "b2f00204-bbbb-4b22-b222-000000000014",
    "type": "expense",
    "amount": 70,
    "category": "transport",
    "description": "Fuel and public transport",
    "date": "2025-04-06T08:30:00.000Z"
  },
  {
    "id": "b2f00205-bbbb-4b22-b222-000000000015",
    "type": "income",
    "amount": 250,
    "category": "other",
    "description": "Digital product sales",
    "date": "2025-05-18T17:20:00.000Z"
  },
  {
    "id": "b2f00206-bbbb-4b22-b222-000000000016",
    "type": "expense",
    "amount": 110,
    "category": "utilities",
    "description": "Internet and phone bill",
    "date": "2025-06-09T21:00:00.000Z"
  },
  {
    "id": "b2f00207-bbbb-4b22-b222-000000000017",
    "type": "income",
    "amount": 600,
    "category": "other",
    "description": "Bonus payment",
    "date": "2025-07-22T10:10:00.000Z"
  },
  {
    "id": "b2f00208-bbbb-4b22-b222-000000000018",
    "type": "expense",
    "amount": 140,
    "category": "entertainment",
    "description": "Concert and events",
    "date": "2025-08-30T23:00:00.000Z"
  },
  {
    "id": "b2f00209-bbbb-4b22-b222-000000000019",
    "type": "income",
    "amount": 180,
    "category": "other",
    "description": "Marketplace sales",
    "date": "2025-12-05T09:30:00.000Z"
  },
  {
    "id": "b2f00210-bbbb-4b22-b222-000000000020",
    "type": "expense",
    "amount": 95,
    "category": "shopping",
    "description": "Home supplies purchase",
    "date": "2025-12-12T18:50:00.000Z"
  },

  {
    "id": "c3f00301-cccc-4c33-b333-000000000021",
    "type": "income",
    "amount": 1400,
    "category": "other",
    "description": "Monthly income payment",
    "date": "2026-01-02T07:00:00.000Z"
  },
  {
    "id": "c3f00302-cccc-4c33-b333-000000000022",
    "type": "expense",
    "amount": 50,
    "category": "food",
    "description": "Weekly grocery shopping",
    "date": "2026-01-06T16:00:00.000Z"
  },
  {
    "id": "c3f00303-cccc-4c33-b333-000000000023",
    "type": "income",
    "amount": 350,
    "category": "other",
    "description": "Client project payment",
    "date": "2026-01-08T11:30:00.000Z"
  },
  {
    "id": "c3f00304-cccc-4c33-b333-000000000024",
    "type": "expense",
    "amount": 65,
    "category": "transport",
    "description": "Transportation expenses",
    "date": "2026-01-10T09:00:00.000Z"
  },
  {
    "id": "c3f00305-cccc-4c33-b333-000000000025",
    "type": "income",
    "amount": 220,
    "category": "other",
    "description": "Online service earnings",
    "date": "2026-01-11T14:45:00.000Z"
  },
  {
    "id": "c3f00306-cccc-4c33-b333-000000000026",
    "type": "expense",
    "amount": 100,
    "category": "utilities",
    "description": "Monthly utility expenses",
    "date": "2026-01-12T20:10:00.000Z"
  },
  {
    "id": "c3f00307-cccc-4c33-b333-000000000027",
    "type": "income",
    "amount": 480,
    "category": "other",
    "description": "Extra work income",
    "date": "2026-01-13T10:00:00.000Z"
  },
  {
    "id": "c3f00308-cccc-4c33-b333-000000000028",
    "type": "expense",
    "amount": 130,
    "category": "entertainment",
    "description": "Streaming and subscriptions",
    "date": "2026-01-13T21:00:00.000Z"
  },
  {
    "id": "c3f00309-cccc-4c33-b333-000000000029",
    "type": "income",
    "amount": 160,
    "category": "other",
    "description": "Small business profit",
    "date": "2026-01-14T08:30:00.000Z"
  },
  {
    "id": "c3f00310-cccc-4c33-b333-000000000030",
    "type": "expense",
    "amount": 85,
    "category": "health",
    "description": "Medical supplies purchase",
    "date": "2026-01-14T19:00:00.000Z"
  },
  {
    "id": "c3f00310-cccc-4c33-b333-000000000030",
    "type": "expense",
    "amount": 85,
    "category": "Sports",
    "description": "buy ball",
    "date": "2026-01-14T19:00:00.000Z"
  }
  
]
